hexfarm/__init__.py
hexfarm/__main__.py
hexfarm/__version__.py
hexfarm/_version.py
hexfarm/cli.py
hexfarm/condor.py
hexfarm/config.py
hexfarm/conversion.py
hexfarm/io.py
hexfarm/optimization.py
hexfarm/root.py
hexfarm/shell.py
hexfarm/util.py
hexfarm/condor/__init__.py
hexfarm/condor/core.py
hexfarm/condor/daemon.py
hexfarm/experimental/__init__.py
hexfarm/ml/__init__.py
tests/condor/__init__.py
hexfarm-0.0.7.dist-info/LICENSE
hexfarm-0.0.7.dist-info/METADATA
hexfarm-0.0.7.dist-info/WHEEL
hexfarm-0.0.7.dist-info/top_level.txt
hexfarm-0.0.7.dist-info/RECORD
