Metadata-Version: 2.1
Name: hexfarm
Version: 0.0.7
Summary: Rutgers HEX Computing Utility Library
Home-page: https://github.com/bhgomes/hexfarm
Author: Brandon Gomes
Author-email: bhgomes.github@gmail.com
License: MIT
Platform: UNKNOWN
Classifier: License :: OSI Approved :: MIT License
Classifier: Programming Language :: Python
Classifier: Programming Language :: Python :: 3
Classifier: Programming Language :: Python :: 3 :: Only
Classifier: Programming Language :: Python :: 3.6
Classifier: Programming Language :: Python :: 3.7
Classifier: Development Status :: 1 - Planning
Classifier: Intended Audience :: Developers
Classifier: Intended Audience :: Science/Research
Classifier: Topic :: Scientific/Engineering :: Physics
Requires-Python: >=3.6.0
Requires-Dist: scipy
Requires-Dist: numpy
Requires-Dist: sympy
Requires-Dist: pandas
Requires-Dist: h5py
Requires-Dist: pint
Requires-Dist: uncertainties
Requires-Dist: pymc3
Requires-Dist: ipykernel
Requires-Dist: matplotlib
Requires-Dist: dask
Requires-Dist: scikit-hep
Requires-Dist: scikit-learn
Requires-Dist: scikit-optimize
Requires-Dist: boltons
Requires-Dist: aenum
Requires-Dist: uproot
Requires-Dist: histbook
Requires-Dist: rootpy
Requires-Dist: particle
Requires-Dist: numpythia
Requires-Dist: formulate
Requires-Dist: iminuit
Requires-Dist: keras
Requires-Dist: tensorflow
Requires-Dist: dataclasses
Requires-Dist: paramiko
Requires-Dist: keyring
Requires-Dist: inflection
Provides-Extra: condor
Requires-Dist: htcondor ; extra == 'condor'
